compiler/__init__.py
compiler/build_api.py
compiler/build_methods.py
compiler/build_types.py
tgrambot/__init__.py
tgrambot/bot.py
tgrambot/dispatcher.py
tgrambot/filters.py
tgrambot/methods.py
tgrambot/utils.py
tgrambot/errors/__init__.py
tgrambot/errors/telegram_error.py
tgrambot/handlers/__init__.py
tgrambot/handlers/callback_handler.py
tgrambot/handlers/handler.py
tgrambot/handlers/message_handler.py
tgrambot/types/__init__.py
tgrambot/types/base.py
tgrambot/types/tg_types.py
TGramBot-0.0.1a9.dist-info/METADATA
TGramBot-0.0.1a9.dist-info/WHEEL
TGramBot-0.0.1a9.dist-info/top_level.txt
TGramBot-0.0.1a9.dist-info/RECORD
