Metadata-Version: 2.1
Name: TGramBot
Version: 0.0.1a9
Summary: Partially Auto-generated and asynchronous Minimal Telegram BOT API framework in Python for bots
Home-page: https://github.com/KeralaBots
Author: Anand
Author-email: anandpskerala@gmail.com
License: LGPLv3
Download-URL: https://github.com/KeralaBots/TgramBot/releases/latest
Project-URL: Tracker, https://github.com/KeralaBots/Tgrambot/issues
Project-URL: Community, https://t.me/Keralasbots
Project-URL: Source, https://github.com/Keralabots/Tgrambot
Keywords: telegram chat messenger bot api library python
Platform: UNKNOWN
Classifier: Development Status :: 3 - Alpha
Classifier: Intended Audience :: Developers
Classifier: Natural Language :: English
Classifier: License :: OSI Approved :: GNU Lesser General Public License v3 (LGPLv3)
Classifier: Operating System :: OS Independent
Classifier: Programming Language :: Python
Classifier: Programming Language :: Python :: 3
Classifier: Programming Language :: Python :: 3.8
Classifier: Programming Language :: Python :: 3.9
Classifier: Programming Language :: Python :: 3.10
Classifier: Programming Language :: Python :: 3.11
Classifier: Programming Language :: Python :: Implementation
Classifier: Programming Language :: Python :: Implementation :: CPython
Classifier: Programming Language :: Python :: Implementation :: PyPy
Classifier: Topic :: Internet
Classifier: Topic :: Communications
Classifier: Topic :: Communications :: Chat
Classifier: Topic :: Software Development :: Libraries
Classifier: Topic :: Software Development :: Libraries :: Python Modules
Classifier: Topic :: Software Development :: Libraries :: Application Frameworks
Requires-Python: >=3.8
Requires-Dist: pydantic
Requires-Dist: httpx[http2]
Requires-Dist: requests
Requires-Dist: beautifulsoup4 (==4.10)
Requires-Dist: html5lib (==1.1)
